crypto_live_trader/__init__.py
crypto_live_trader/binance.py
crypto_live_trader/utils.py
crypto_live_trader-0.0.1.dist-info/METADATA
crypto_live_trader-0.0.1.dist-info/WHEEL
crypto_live_trader-0.0.1.dist-info/top_level.txt
crypto_live_trader-0.0.1.dist-info/RECORD
