Metadata-Version: 2.4
Name: crypto-live-trader
Version: 0.0.1
Summary: ???
Home-page: https://github.com/SerenaTradingResearch/crypto-live-trader
Author: Ricky Ding
Author-email: e0134117@u.nus.edu
License: MIT
Keywords: ???
Classifier: Programming Language :: Python :: 3
Classifier: Intended Audience :: Financial and Insurance Industry
Classifier: License :: OSI Approved :: MIT License
Requires-Python: >=3.8
Dynamic: author
Dynamic: author-email
Dynamic: classifier
Dynamic: description
Dynamic: description-content-type
Dynamic: home-page
Dynamic: keywords
Dynamic: license
Dynamic: requires-python
Dynamic: summary
